lb_dsnd_distributions/Binomialdistribution.py
lb_dsnd_distributions/Gaussiandistribution.py
lb_dsnd_distributions/Generaldistribution.py
lb_dsnd_distributions/__init__.py
lb_dsnd_distributions-0.0.3.dist-info/METADATA
lb_dsnd_distributions-0.0.3.dist-info/WHEEL
lb_dsnd_distributions-0.0.3.dist-info/top_level.txt
lb_dsnd_distributions-0.0.3.dist-info/RECORD
