Metadata-Version: 2.1
Name: lb-dsnd-distributions
Version: 0.0.3
Summary: Gaussian & Binomial distributions
Home-page: UNKNOWN
Author: Lisa Banh
Author-email: contact.lisabanh@gmail.com
License: UNKNOWN
Platform: UNKNOWN
Classifier: Programming Language :: Python :: 3
Classifier: License :: OSI Approved :: MIT License
Classifier: Operating System :: OS Independent
